qibo/__init__.py
qibo/backends/__init__.py
qibo/backends/_clifford_operations.py
qibo/backends/_hamming_weight_operations.py
qibo/backends/abstract.py
qibo/backends/clifford.py
qibo/backends/einsum_utils.py
qibo/backends/hamming_weight.py
qibo/backends/npmatrices.py
qibo/backends/numpy.py
qibo/backends/qulacs.py
qibo/callbacks.py
qibo/config.py
qibo/derivative.py
qibo/gates/__init__.py
qibo/gates/abstract.py
qibo/gates/channels.py
qibo/gates/gates.py
qibo/gates/measurements.py
qibo/gates/special.py
qibo/hamiltonians/__init__.py
qibo/hamiltonians/abstract.py
qibo/hamiltonians/adiabatic.py
qibo/hamiltonians/hamiltonians.py
qibo/hamiltonians/models.py
qibo/hamiltonians/terms.py
qibo/measurements.py
qibo/models/__init__.py
qibo/models/_openqasm.py
qibo/models/circuit.py
qibo/models/distcircuit.py
qibo/models/encodings.py
qibo/models/error_mitigation.py
qibo/models/evolution.py
qibo/models/grover.py
qibo/models/hep.py
qibo/models/iqae.py
qibo/models/qcnn.py
qibo/models/qft.py
qibo/models/tsp.py
qibo/models/utils.py
qibo/models/variational.py
qibo/noise.py
qibo/optimizers.py
qibo/parallel.py
qibo/parameter.py
qibo/quantum_info/__init__.py
qibo/quantum_info/_clifford_utils.py
qibo/quantum_info/_quantum_info.py
qibo/quantum_info/basis.py
qibo/quantum_info/clifford.py
qibo/quantum_info/entanglement.py
qibo/quantum_info/entropies.py
qibo/quantum_info/hamming_weight.py
qibo/quantum_info/linalg_operations.py
qibo/quantum_info/metrics.py
qibo/quantum_info/quantum_networks.py
qibo/quantum_info/random_ensembles.py
qibo/quantum_info/superoperator_transformations.py
qibo/quantum_info/utils.py
qibo/result.py
qibo/solvers.py
qibo/symbols.py
qibo/tomography/__init__.py
qibo/tomography/gate_set_tomography.py
qibo/transpiler/__init__.py
qibo/transpiler/_exceptions.py
qibo/transpiler/abstract.py
qibo/transpiler/asserts.py
qibo/transpiler/blocks.py
qibo/transpiler/decompositions.py
qibo/transpiler/optimizer.py
qibo/transpiler/pipeline.py
qibo/transpiler/placer.py
qibo/transpiler/qiskit.py
qibo-0.2.23.dist-info/METADATA
qibo-0.2.23.dist-info/WHEEL
qibo-0.2.23.dist-info/licenses/LICENSE
qibo-0.2.23.dist-info/RECORD
