Metadata-Version: 2.4
Name: qibo
Version: 0.2.23
Summary: A framework for quantum computing with hardware acceleration.
License: Apache-2.0
License-File: LICENSE
Author: The Qibo team
Requires-Python: >=3.10,<3.14
Classifier: License :: OSI Approved :: Apache Software License
Classifier: Programming Language :: Python :: 3
Classifier: Programming Language :: Python :: 3.10
Classifier: Programming Language :: Python :: 3.11
Classifier: Programming Language :: Python :: 3.12
Classifier: Programming Language :: Python :: 3.13
Classifier: Topic :: Scientific/Engineering :: Physics
Provides-Extra: cudaq
Provides-Extra: qinfo
Provides-Extra: qir
Provides-Extra: qulacs
Requires-Dist: cma (>=3.4.0,<4.0.0)
Requires-Dist: joblib (>=1.4.2,<2.0.0)
Requires-Dist: networkx (>=3.2.1,<4.0.0)
Requires-Dist: numpy (>=2.0.0,<3.0.0)
Requires-Dist: openqasm3[parser] (>=1.0.1,<2.0.0)
Requires-Dist: optuna (>=4.2.1,<5.0.0)
Requires-Dist: qbraid[cudaq, qir] (>=0.10.0,<0.11.0) ; extra == "cudaq" and extra == "qir"
Requires-Dist: qbraid[cudaq] (>=0.10.0,<0.11.0) ; extra == "cudaq"
Requires-Dist: qbraid[qir] (>=0.10.0,<0.11.0) ; extra == "qir"
Requires-Dist: qulacs (>=0.6.4,<0.7.0) ; (python_version < "3.13") and (extra == "qulacs")
Requires-Dist: scipy (>=1.15.2,<2.0.0)
Requires-Dist: sympy (>=1.13.1,<2.0.0)
Requires-Dist: tabulate (>=0.9.0,<0.10.0)
Project-URL: Documentation, https://qibo.science/docs/qibo/stable
Project-URL: Homepage, https://qibo.science/
Project-URL: Repository, https://github.com/qiboteam/qibo/
